pixel_world/__init__.py
pixel_world/env_utils.py
pixel_world-1.3.0.dist-info/METADATA
pixel_world-1.3.0.dist-info/WHEEL
pixel_world-1.3.0.dist-info/top_level.txt
pixel_world-1.3.0.dist-info/RECORD
